small_pipe/__init__.py
small_pipe/small_pipe.py
small_pipe-0.1.0.dist-info/METADATA
small_pipe-0.1.0.dist-info/WHEEL
small_pipe-0.1.0.dist-info/licenses/LICENSE
small_pipe-0.1.0.dist-info/RECORD
