Metadata-Version: 2.1
Name: small_pipe
Version: 0.1.0
Summary: Pipe your python functions!
Project-URL: Homepage, https://github.com/havelkao/small_pipe
Project-URL: Bug Tracker, https://github.com/havelkao/small_pipe/issues
License-File: LICENSE
Classifier: License :: OSI Approved :: MIT License
Classifier: Operating System :: OS Independent
Classifier: Programming Language :: Python :: 3
Requires-Python: >=3.7
